setup.py
ryan_pypi_test/__init__.py
ryan_pypi_test/example.py
ryan_pypi_test.egg-info/PKG-INFO
ryan_pypi_test.egg-info/SOURCES.txt
ryan_pypi_test.egg-info/dependency_links.txt
ryan_pypi_test.egg-info/top_level.txt