Metadata-Version: 1.0
Name: ryan-pypi-test
Version: 1.0.0
Summary: Test project for PyPI
Home-page: UNKNOWN
Author: UNKNOWN
Author-email: UNKNOWN
License: UNKNOWN
Platform: UNKNOWN
